handsfreed/__init__.py
handsfreed/__main__.py
handsfreed/audio_capture.py
handsfreed/config.py
handsfreed/ipc_models.py
handsfreed/ipc_server.py
handsfreed/logging_setup.py
handsfreed/main.py
handsfreed/output_handler.py
handsfreed/pipeline.py
handsfreed/pipeline_manager.py
handsfreed/state.py
handsfreed/transcriber.py
handsfreed/segmentation/__init__.py
handsfreed/segmentation/fixed.py
handsfreed/segmentation/strategy.py
handsfreed/segmentation/vad.py
handsfreed-0.1.0.dist-info/licenses/LICENSE
handsfreed-0.1.0.dist-info/METADATA
handsfreed-0.1.0.dist-info/WHEEL
handsfreed-0.1.0.dist-info/entry_points.txt
handsfreed-0.1.0.dist-info/top_level.txt
handsfreed-0.1.0.dist-info/RECORD
