Metadata-Version: 2.4
Name: handsfreed
Version: 0.1.0
Summary: Handsfree speech-to-text daemon for Linux
Author-email: Achyudh Ram <mail@achyudh.me>
License-Expression: GPL-3.0-or-later
Project-URL: Homepage, https://github.com/achyudh/handsfree
Project-URL: Repository, https://github.com/achyudh/handsfreed
Project-URL: Issues, https://github.com/achyudh/handsfreed/issues
Keywords: speech-to-text,speech recognition,whisper,transcription,dictation,vad,daemon,linux,offline,real-time
Classifier: Development Status :: 4 - Beta
Classifier: Environment :: No Input/Output (Daemon)
Classifier: Intended Audience :: End Users/Desktop
Classifier: Operating System :: POSIX :: Linux
Classifier: Programming Language :: Python :: 3
Classifier: Programming Language :: Python :: 3.11
Classifier: Topic :: Multimedia :: Sound/Audio :: Speech
Classifier: Topic :: Scientific/Engineering :: Artificial Intelligence
Classifier: Topic :: Utilities
Requires-Python: >=3.11
License-File: LICENSE
Requires-Dist: pydantic>=2.0
Requires-Dist: sounddevice>=0.5
Requires-Dist: numpy>=2.2
Requires-Dist: faster-whisper>=1.2.1
Provides-Extra: dev
Requires-Dist: pytest>=8.3; extra == "dev"
Requires-Dist: pytest-asyncio>=0.26; extra == "dev"
Dynamic: license-file
